sphinx_pangeo_theme/__init__.py
sphinx_pangeo_theme/_version.py
sphinx_pangeo_theme/navbar.html
sphinx_pangeo_theme/srclinks.html
sphinx_pangeo_theme/theme.conf
sphinx_pangeo_theme/static/pangeo-style.css
sphinx_pangeo_theme/static/panton.black-caps.otf
sphinx_pangeo_theme/static/panton.light-caps.otf
sphinx_pangeo_theme/static/small_e_reversed_24px.png
sphinx_pangeo_theme-0.2.dist-info/LICENSE
sphinx_pangeo_theme-0.2.dist-info/METADATA
sphinx_pangeo_theme-0.2.dist-info/WHEEL
sphinx_pangeo_theme-0.2.dist-info/entry_points.txt
sphinx_pangeo_theme-0.2.dist-info/top_level.txt
sphinx_pangeo_theme-0.2.dist-info/RECORD
