Metadata-Version: 2.1
Name: sphinx-pangeo-theme
Version: 0.2
Summary: Pangeo theme for Sphinx
Home-page: https://github.com/pangeo-data/sphinx_pangeo_theme/
Author: Ryan Abernathey
Author-email: rpa@ldeo.columbia.edu
License: MIT
Platform: UNKNOWN
Classifier: Framework :: Sphinx
Classifier: Framework :: Sphinx :: Theme
Classifier: Development Status :: 5 - Production/Stable
Classifier: License :: OSI Approved :: MIT License
Classifier: Environment :: Console
Classifier: Environment :: Web Environment
Classifier: Intended Audience :: Developers
Classifier: Programming Language :: Python :: 2.7
Classifier: Programming Language :: Python :: 3
Classifier: Programming Language :: Python :: 3.3
Classifier: Programming Language :: Python :: 3.4
Classifier: Programming Language :: Python :: 3.5
Classifier: Programming Language :: Python :: 3.6
Classifier: Operating System :: OS Independent
Classifier: Topic :: Documentation
Classifier: Topic :: Software Development :: Documentation
Requires-Dist: sphinx
Requires-Dist: sphinx-bootstrap-theme
